Metadata-Version: 1.1
Name: personal.koder.helloworld
Version: 9.0.0
Summary: Helloworld App DONTUSE for POC
Home-page: UNKNOWN
Author: tevkoder
Author-email: koder@tevora.com
License: GPLv3
Platform: UNKNOWN
Classifier: Development Status :: 4 - Beta
Classifier: Environment :: Console
Classifier: Operating System :: POSIX :: Other
Classifier: Programming Language :: Python :: 3
Classifier: Programming Language :: Python :: 3.3
Classifier: Programming Language :: Python :: 3.4
Classifier: Programming Language :: Python :: 3.5
Classifier: Programming Language :: Python :: 3.7
